micro/__init__.py
micro/__main__.py
micro/api/__init__.py
micro/api/apirest.py
micro/api/celery.py
micro/api/endpoints.py
micro/core/__init__.py
micro/core/celeryapp.py
micro/core/config.py
micro/core/gunicornapp.py
micro/core/logger.py
micro/core/microapp.py
micro/core/params.py
micro/core/setting.py
micro/core/settingbase.py
micro/core/utils.py
micro/core/validate.py
micro/plugin/__init__.py
micro/plugin/pluginbase.py
micro/plugin/pluginmanager.py
tests/api/__init__.py
tests/api/test_apirest.py
tests/api/test_celery.py
tests/api/test_endpoints.py
tests/core/__init__.py
tests/core/test_celeryapp.py
tests/core/test_config.py
tests/core/test_gunicornapp.py
tests/core/test_logger.py
tests/core/test_microapp.py
tests/core/test_params.py
tests/core/test_utils.py
tests/core/test_validate.py
tests/plugin/__init__.py
tests/plugin/test_pluginbase.py
tests/plugin/test_pluginmanager.py
Micro-3.1.0.dist-info/LICENSE
Micro-3.1.0.dist-info/METADATA
Micro-3.1.0.dist-info/WHEEL
Micro-3.1.0.dist-info/entry_points.txt
Micro-3.1.0.dist-info/top_level.txt
Micro-3.1.0.dist-info/RECORD
