Metadata-Version: 1.1
Name: Micro
Version: 3.1.0
Summary: Celery platform to create microservices
Home-page: https://github.com/humu1us/micro
Author: Felipe Ortiz, Pablo Ahumada
Author-email: fortizc@gmail.com, pablo.ahumadadiaz@gmail.com
License: MIT
Keywords: microservices celery
Platform: UNKNOWN
Classifier: Development Status :: 5 - Production/Stable
Classifier: Intended Audience :: Developers
Classifier: Topic :: Software Development
Classifier: Topic :: System
Classifier: License :: OSI Approved :: MIT License
Classifier: Programming Language :: Python :: 3.6
